TensorflowExamplesAymericdamien/README.md
TensorflowExamplesAymericdamien/__init__.py
TensorflowExamplesAymericdamien/__main__.py
TensorflowExamplesAymericdamien/file.epub
TensorflowExamplesAymericdamien/index.html
TensorflowExamplesAymericdamien/css/__init__.py
TensorflowExamplesAymericdamien/css/annotations.css
TensorflowExamplesAymericdamien/css/main.css
TensorflowExamplesAymericdamien/css/normalize.css
TensorflowExamplesAymericdamien/css/popup.css
TensorflowExamplesAymericdamien/font/__init__.py
TensorflowExamplesAymericdamien/font/fontello.eot
TensorflowExamplesAymericdamien/font/fontello.svg
TensorflowExamplesAymericdamien/font/fontello.ttf
TensorflowExamplesAymericdamien/font/fontello.woff
TensorflowExamplesAymericdamien/img/__init__.py
TensorflowExamplesAymericdamien/img/annotator-glyph-sprite.png
TensorflowExamplesAymericdamien/img/annotator-icon-sprite.png
TensorflowExamplesAymericdamien/img/apple-touch-icon.png
TensorflowExamplesAymericdamien/img/cancelfullscreen.png
TensorflowExamplesAymericdamien/img/close.png
TensorflowExamplesAymericdamien/img/fullscreen.png
TensorflowExamplesAymericdamien/img/loader.gif
TensorflowExamplesAymericdamien/img/menu-icon.png
TensorflowExamplesAymericdamien/img/save.png
TensorflowExamplesAymericdamien/img/saved.png
TensorflowExamplesAymericdamien/img/settings-s.png
TensorflowExamplesAymericdamien/img/settings.png
TensorflowExamplesAymericdamien/img/star.png
TensorflowExamplesAymericdamien/js/__init__.py
TensorflowExamplesAymericdamien/js/epub.js
TensorflowExamplesAymericdamien/js/epub.min.js
TensorflowExamplesAymericdamien/js/epub.min.map
TensorflowExamplesAymericdamien/js/hooks.min.js
TensorflowExamplesAymericdamien/js/hooks.min.map
TensorflowExamplesAymericdamien/js/reader.js
TensorflowExamplesAymericdamien/js/reader.js.map
TensorflowExamplesAymericdamien/js/reader.min.js
TensorflowExamplesAymericdamien/js/reader.min.map
TensorflowExamplesAymericdamien/js/hooks/__init__.py
tensorflow_examples_aymericdamien-2024.3.3.0.dist-info/METADATA
tensorflow_examples_aymericdamien-2024.3.3.0.dist-info/WHEEL
tensorflow_examples_aymericdamien-2024.3.3.0.dist-info/entry_points.txt
tensorflow_examples_aymericdamien-2024.3.3.0.dist-info/top_level.txt
tensorflow_examples_aymericdamien-2024.3.3.0.dist-info/RECORD
